graphenetools/__init__.py
graphenetools/__main__.py
graphenetools/gt.py
graphenetools/gt_c_one_third_commensurate_command.py
graphenetools/gt_c_one_third_commensurate_command_plot.py
graphenetools/gt_roughly_square.py
graphenetools/gt_roughly_square_plot.py
graphenetools_py-0.10.0.dist-info/LICENSE
graphenetools_py-0.10.0.dist-info/METADATA
graphenetools_py-0.10.0.dist-info/WHEEL
graphenetools_py-0.10.0.dist-info/entry_points.txt
graphenetools_py-0.10.0.dist-info/top_level.txt
graphenetools_py-0.10.0.dist-info/RECORD
