Metadata-Version: 2.1
Name: graphenetools-py
Version: 0.10.0
Summary: Tools for generating parameters for helium on uniaxially strained graphene simulations using quantum Monte Carlo software hosted at https://code.delmaestro.org and plots of the helium graphene interaction
Home-page: https://github.com/nscottnichols/graphenetools-py
Author: Nathan Nichols
Author-email: Nathan.Nichols@uvm.edu
License: MIT
Platform: UNKNOWN
Classifier: License :: OSI Approved :: MIT License
Classifier: Programming Language :: Python :: 3
Classifier: Programming Language :: Python :: 3.7
Requires-Dist: numpy
Requires-Dist: matplotlib
Requires-Dist: scipy
